OhMyProfiles/__init__.py
OhMyProfiles/omp.py
OhMyProfiles-0.19.dist-info/LICENSE
OhMyProfiles-0.19.dist-info/METADATA
OhMyProfiles-0.19.dist-info/WHEEL
OhMyProfiles-0.19.dist-info/entry_points.txt
OhMyProfiles-0.19.dist-info/top_level.txt
OhMyProfiles-0.19.dist-info/RECORD
