Metadata-Version: 2.1
Name: OhMyProfiles
Version: 0.19
Summary: A  module for manager profile
Home-page: https://github.com/johnpoint/Oh-My-Profiles
Author: johnpoint
Author-email: me@lvcshu.com
License: GPL-3.0
Platform: UNKNOWN
Requires: hashlib
Requires: os
Requires: sys
Requires: json
Requires: uuid
Requires: zipfile
Requires: tqdm
Requires: Fernet
License-File: LICENSE
